setup.py
wdmmgext/__init__.py
wdmmgext.egg-info/PKG-INFO
wdmmgext.egg-info/SOURCES.txt
wdmmgext.egg-info/dependency_links.txt
wdmmgext.egg-info/entry_points.txt
wdmmgext.egg-info/not-zip-safe
wdmmgext.egg-info/requires.txt
wdmmgext.egg-info/top_level.txt
wdmmgext/clean/__init__.py
wdmmgext/clean/clean_up_barnet.py
wdmmgext/clean/cra2010_clean.py
wdmmgext/load/__init__.py
wdmmgext/load/barnet.py
wdmmgext/load/cofog.py
wdmmgext/load/cra.py
wdmmgext/load/cra2010.py
wdmmgext/load/departments.py
wdmmgext/load/dfid.py
wdmmgext/load/fts.py
wdmmgext/load/gla.py
wdmmgext/load/hmt.py
wdmmgext/load/israel.py
wdmmgext/load/ordnance.py
wdmmgext/load/spain.py
wdmmgext/load/uganda.py
wdmmgext/load/util.py
wdmmgext/load/bmf/__init__.py
wdmmgext/load/bmf/colorize.py
wdmmgext/load/bmf/load.py
wdmmgext/load/bmf/parse.py
wdmmgext/load/bmf/plan.py
wdmmgext/tests/__init__.py
wdmmgext/tests/load/__init__.py
wdmmgext/tests/load/test_barnet.py
wdmmgext/tests/load/test_departments.py
wdmmgext/tests/load/test_dfid.py
wdmmgext/tests/load/test_israel.py
wdmmgext/tests/load/test_spain.py
wdmmgext/tests/load/test_uganda.py