Metadata-Version: 1.0
Name: wdmmgext
Version: 0.1
Summary: Where Does My Money Go (WDMMG) Extension Code
Home-page: http://www.wheredoesmymoneygo.org/
Author: Open Knowledge Foundation (Where Does My Money Go)
Author-email: wdmmg@okfn.org
License: UNKNOWN
Platform: UNKNOWN
